{
  "project_info": {
    "project_number": "542181398313",
    "firebase_url": "https://sfit-canteen.firebaseio.com",
    "project_id": "sfit-canteen",
    "storage_bucket": "sfit-canteen.appspot.com"
  },
  "client": [
    {
      "client_info": {
        "mobilesdk_app_id": "1:542181398313:android:00d1c6bec3cfb29fc80938",
        "android_client_info": {
          "package_name": "com.example.sfit_canteen_app_new"
        }
      },
      "oauth_client": [
        {
          "client_id": "542181398313-9diua38m7ehuabkm78g9blnrpi8s21k1.apps.googleusercontent.com",
          "client_type": 3
        }
      ],
      "api_key": [
        {
          "current_key": "AIzaSyCKJniDLDNH2-oVbXFMORuMPU65pI0mYL0"
        }
      ],
      "services": {
        "appinvite_service": {
          "other_platform_oauth_client": [
            {
              "client_id": "542181398313-9diua38m7ehuabkm78g9blnrpi8s21k1.apps.googleusercontent.com",
              "client_type": 3
            }
          ]
        }
      }
    }
  ],
  "configuration_version": "1"
}